lurl/__init__.py
lurl/args_parser.py
lurl/har-to-curl.js
lurl/harcurl.js
lurl/interactive.py
lurl/main.py
lurl/multihar.py
lurl/requrl.py
lurl/tkp_struct.py
lurl-0.1.2.dist-info/METADATA
lurl-0.1.2.dist-info/WHEEL
lurl-0.1.2.dist-info/entry_points.txt
lurl-0.1.2.dist-info/top_level.txt
lurl-0.1.2.dist-info/RECORD
