Metadata-Version: 2.1
Name: lurl
Version: 0.1.2
Summary: cURL please....
Home-page: UNKNOWN
Author: Fernanda Panca Prima
Author-email: pancaprima8@gmail.com
License: MIT
Platform: UNKNOWN
Classifier: License :: OSI Approved :: MIT License
Classifier: Programming Language :: Python :: 3
Requires-Python: >=3.6
Requires-Dist: requests
Requires-Dist: puncurl
Requires-Dist: Naked
Requires-Dist: inquirer
